datesort/__init__.py
datesort/plugin.py
mkdocs_datesort_plugin-0.0.2.dist-info/METADATA
mkdocs_datesort_plugin-0.0.2.dist-info/WHEEL
mkdocs_datesort_plugin-0.0.2.dist-info/entry_points.txt
mkdocs_datesort_plugin-0.0.2.dist-info/top_level.txt
mkdocs_datesort_plugin-0.0.2.dist-info/RECORD
